subprompt/__init__.py
subprompt/subprompt.py
subprompt-0.0.9.dist-info/LICENSE
subprompt-0.0.9.dist-info/METADATA
subprompt-0.0.9.dist-info/WHEEL
subprompt-0.0.9.dist-info/entry_points.txt
subprompt-0.0.9.dist-info/top_level.txt
subprompt-0.0.9.dist-info/RECORD
